fast_tradier/FastTradierAsyncClient.py
fast_tradier/FastTradierClient.py
fast_tradier/__init__.py
fast_tradier/interfaces/IBrokerAsyncClient.py
fast_tradier/interfaces/IBrokerClient.py
fast_tradier/interfaces/IModel.py
fast_tradier/interfaces/IRealTimeQuoteProvider.py
fast_tradier/interfaces/__init__.py
fast_tradier/models/DataClassModelBase.py
fast_tradier/models/ModelBase.py
fast_tradier/models/__init__.py
fast_tradier/models/account/AccountBalance.py
fast_tradier/models/account/AccountOrder.py
fast_tradier/models/account/Position.py
fast_tradier/models/account/__init__.py
fast_tradier/models/market_data/Hlocv.py
fast_tradier/models/market_data/Quote.py
fast_tradier/models/market_data/TradierQuote.py
fast_tradier/models/market_data/__init__.py
fast_tradier/models/trading/Duration.py
fast_tradier/models/trading/EquityOrder.py
fast_tradier/models/trading/Interval.py
fast_tradier/models/trading/OptionOrder.py
fast_tradier/models/trading/OrderBase.py
fast_tradier/models/trading/PriceTypes.py
fast_tradier/models/trading/Sides.py
fast_tradier/models/trading/TOSTradierConverter.py
fast_tradier/models/trading/__init__.py
fast_tradier/playground/test1.py
fast_tradier/utils/OptionUtils.py
fast_tradier/utils/TimeUtils.py
fast_tradier/utils/YFinanceQuoteProvider.py
fast_tradier/utils/__init__.py
fast_tradier_client-0.3.3.dist-info/LICENSE
fast_tradier_client-0.3.3.dist-info/METADATA
fast_tradier_client-0.3.3.dist-info/WHEEL
fast_tradier_client-0.3.3.dist-info/top_level.txt
fast_tradier_client-0.3.3.dist-info/RECORD
