Metadata-Version: 2.1
Name: fast_tradier_client
Version: 0.3.3
Summary: A Tradier client for trading stocks and options through Tradier API
Home-page: https://pypi.org/project/fast-tradier-client/
Author: Tony W
Author-email: Tony Wang <ivytony@gmail.com>
Project-URL: Homepage, https://bitbucket.org/rcholic/fast-tradier-client
Project-URL: Bug Tracker, https://bitbucket.org/rcholic/fast-tradier-client/jira?statuses=new&statuses=indeterminate&sort=-updated&page=1
Keywords: python,fast-tradier-client,tradier
Classifier: Programming Language :: Python :: 3
Classifier: License :: OSI Approved :: MIT License
Classifier: Operating System :: OS Independent
Requires-Python: >=3.7
License-File: LICENSE
Requires-Dist: jsonpickle
Requires-Dist: httpx
Requires-Dist: arrow
Requires-Dist: autoscraper
Requires-Dist: pandas
Requires-Dist: python-interface
Requires-Dist: pytest
Requires-Dist: pytest-httpx
Requires-Dist: pytest-asyncio
